IDEAL_NPU/__init__.py
IDEAL_NPU/funs.py
IDEAL_NPU/setup.py
IDEAL_NPU/cluster/FCDMF.py
IDEAL_NPU/cluster/FCDMF_.cp37-win_amd64.pyd
IDEAL_NPU/cluster/RCC.py
IDEAL_NPU/cluster/SC.py
IDEAL_NPU/cluster/SSC.py
IDEAL_NPU/cluster/__init__.py
IDEAL_NPU/cluster/_agci_emb.cp37-win_amd64.pyd
IDEAL_NPU/cluster/_edg.py
IDEAL_NPU/cluster/_pcn.py
IDEAL_NPU/cluster/agci.py
IDEAL_NPU/cluster/finch.py
IDEAL_NPU/cluster/setup.py
IDEAL_NPU/cluster/SNNDPC/Classifier.py
IDEAL_NPU/cluster/SNNDPC/Core.py
IDEAL_NPU/cluster/SNNDPC/Option.py
IDEAL_NPU/cluster/SNNDPC/__init__.py
IDEAL_NPU/dataset/Agg.mat
IDEAL_NPU/dataset/USPS.mat
IDEAL_NPU/dataset/USPS.txt
IDEAL_NPU/dataset/crescentfullmoon.mat
IDEAL_NPU/demo/demo_AGCI.py
IDEAL_NPU/demo/demo_DNC.py
IDEAL_NPU/demo/demo_EDG.py
IDEAL_NPU/demo/demo_FCDMF.py
IDEAL_NPU/demo/demo_FINCH.py
IDEAL_NPU/demo/demo_ISR.py
IDEAL_NPU/demo/demo_PCN.py
IDEAL_NPU/demo/demo_RCC.py
IDEAL_NPU/demo/demo_SC.py
IDEAL_NPU/demo/demo_SNN.py
IDEAL_NPU/demo/demo_SSC.py
IDEAL_NPU-0.4.3.dist-info/METADATA
IDEAL_NPU-0.4.3.dist-info/WHEEL
IDEAL_NPU-0.4.3.dist-info/top_level.txt
IDEAL_NPU-0.4.3.dist-info/RECORD
