Metadata-Version: 2.1
Name: IDEAL-NPU
Version: 0.4.3
Summary: A Python module for machine learning
Home-page: https://github.com/ShenfeiPei/IDEAL_NPU
Author: Shenfei Pei
Author-email: shenfeipei@gmail.com
License: UNKNOWN
Platform: UNKNOWN
Classifier: Intended Audience :: Science/Research
Classifier: Intended Audience :: Developers
Classifier: License :: OSI Approved :: MIT License
Classifier: Programming Language :: C
Classifier: Programming Language :: Python
Classifier: Topic :: Software Development
Classifier: Topic :: Scientific/Engineering
Classifier: Operating System :: Microsoft :: Windows
Classifier: Programming Language :: Python :: 3.7
Classifier: Programming Language :: Python :: Implementation :: CPython
Requires-Python: >=3.6
Requires-Dist: numpy (>=1.16.5)
Requires-Dist: scipy (>=1.3.1)
Requires-Dist: pandas (>=0.25.1)
Requires-Dist: scikit-learn (>=0.21.3)
